blinkcheck/__init__.py
blinkcheck/console.py
blinkcheck-0.1.1.dist-info/entry_points.txt
blinkcheck-0.1.1.dist-info/LICENSE.txt
blinkcheck-0.1.1.dist-info/WHEEL
blinkcheck-0.1.1.dist-info/METADATA
blinkcheck-0.1.1.dist-info/RECORD
