Metadata-Version: 2.1
Name: blinkcheck
Version: 0.1.1
Summary: Basic link checker
Home-page: https://github.com/blu3r4y/pyforever
License: MIT
Author: Mario Kahlhofer
Author-email: mario.kahlhofer@gmail.com
Requires-Python: >=3.8,<4.0
Classifier: License :: OSI Approved :: MIT License
Classifier: Programming Language :: Python :: 3
Classifier: Programming Language :: Python :: 3.8
Classifier: Programming Language :: Python :: 3.9
Requires-Dist: requests (>=2,<3)
Project-URL: Repository, https://github.com/blu3r4y/pyforever
